excursor/__init__.py
excursor/core/_process.py
excursor/core/_process_39.py
excursor/core/http.py
excursor/core/installer.py
excursor/core/installer_39.py
excursor/core/process.py
excursor/example_ds/data1.ndjson
excursor/example_ds/data1_pretty.json
excursor/func.py
excursor/learn_ray.py
excursor/scripts/install.py
excursor/services/datetime_svc.py
excursor-0.1.2.dist-info/METADATA
excursor-0.1.2.dist-info/WHEEL
excursor-0.1.2.dist-info/entry_points.txt
excursor-0.1.2.dist-info/RECORD
