Metadata-Version: 2.1
Name: excursor
Version: 0.1.2
Summary: 
License: Apache-2.0
Author: Sean Toner
Author-email: placeoftheway@gmail.com
Requires-Python: >=3.9,<3.13
Classifier: License :: OSI Approved :: Apache Software License
Classifier: Programming Language :: Python :: 3
Classifier: Programming Language :: Python :: 3.9
Classifier: Programming Language :: Python :: 3.10
Classifier: Programming Language :: Python :: 3.11
Provides-Extra: data
Provides-Extra: ml
Provides-Extra: serve
Provides-Extra: viz
Requires-Dist: daak (>=0.1.1,<0.2.0)
Requires-Dist: duckdb (>=0.9.0,<0.10.0) ; extra == "data"
Requires-Dist: fastapi (>=0.101.1,<0.102.0) ; extra == "serve"
Requires-Dist: httpx (>=0.24,<0.25) ; extra == "serve"
Requires-Dist: ipykernel (>=6.25.2,<7.0.0)
Requires-Dist: ipywidgets (>=8.0,<9.0) ; extra == "viz"
Requires-Dist: jupyterlab (>=4.0,<5.0) ; extra == "viz"
Requires-Dist: numpy (>=1.26,<2.0)
Requires-Dist: plotly (>=5.15,<6.0) ; extra == "viz"
Requires-Dist: polars[numpy,pandas,pyarrow] (>=0.18.4,<0.19.0) ; extra == "data"
Requires-Dist: pyarrow (>=13.0.0,<14.0.0) ; extra == "data"
Requires-Dist: pydantic (>=2.4,<3.0) ; extra == "serve"
Requires-Dist: sympy (>=1.12,<2.0)
Requires-Dist: torch (>=2.1.0,<3.0.0) ; extra == "ml"
Requires-Dist: uvicorn[standard] (>=0.23.2,<0.24.0) ; extra == "serve"
